airflow_dag/__init__.py
airflow_dag/__version__.py
airflow_dag/cli.py
airflow_dag-0.1.0.dist-info/LICENSE
airflow_dag-0.1.0.dist-info/METADATA
airflow_dag-0.1.0.dist-info/WHEEL
airflow_dag-0.1.0.dist-info/entry_points.txt
airflow_dag-0.1.0.dist-info/top_level.txt
airflow_dag-0.1.0.dist-info/RECORD
