Metadata-Version: 2.1
Name: airflow-dag
Version: 0.1.0
Summary: A tool to manage Airflow dags.
Home-page: https://github.com/vinayak-mehta/airflow-dag
Author: Vinayak Mehta
Author-email: vmehta94@gmail.com
License: Apache 2.0
Platform: UNKNOWN
Classifier: License :: OSI Approved :: Apache Software License
Classifier: Programming Language :: Python :: 3.6
Classifier: Programming Language :: Python :: 3.7
Classifier: Programming Language :: Python :: 3.8
Classifier: Programming Language :: Python :: 3.9
Provides-Extra: dev
